jupyweave/__init__.py
jupyweave/__main__.py
jupyweave/client_wrapper.py
jupyweave/document_processor.py
jupyweave/install_files.py
jupyweave/jupyweave.py
jupyweave/kernel_client_manager.py
jupyweave/kernel_engine.py
jupyweave/output_manager.py
jupyweave/processing_manager.py
jupyweave/result_manager.py
jupyweave/results_processor.py
jupyweave/configs/defconfig.json
jupyweave/configs/knitr_config.json
jupyweave/exceptions/__init__.py
jupyweave/exceptions/engine_errors.py
jupyweave/exceptions/processor_errors.py
jupyweave/exceptions/settings_errors.py
jupyweave/exceptions/snippet_errors.py
jupyweave/processors/__init__.py
jupyweave/processors/html_processor.py
jupyweave/processors/latex_processor.py
jupyweave/processors/markdown_processor.py
jupyweave/processors/processor.py
jupyweave/settings/__init__.py
jupyweave/settings/align_types.py
jupyweave/settings/environment.py
jupyweave/settings/group_names.py
jupyweave/settings/output_settings.py
jupyweave/settings/output_types.py
jupyweave/settings/pattern.py
jupyweave/settings/settings.py
jupyweave/settings/snippet.py
jupyweave/settings/snippets.py
jupyweave/settings/timeouts.py
jupyweave/settings/validator.py
jupyweave/user_processors/highlight_html_processor.py
jupyweave/user_processors/no_escape_html_processor.py
jupyweave/user_processors/no_escape_latex_processor.py
jupyweave/user_processors/no_escape_markdown_processor.py
jupyweave/user_processors/python_latex_processor.py
jupyweave/user_processors/r_latex_processor.py
jupyweave/user_processors/sql_html_processor.py
jupyweave/user_processors/sql_latex_processor.py
jupyweave-0.2.6.dist-info/DESCRIPTION.rst
jupyweave-0.2.6.dist-info/METADATA
jupyweave-0.2.6.dist-info/RECORD
jupyweave-0.2.6.dist-info/WHEEL
jupyweave-0.2.6.dist-info/entry_points.txt
jupyweave-0.2.6.dist-info/metadata.json
jupyweave-0.2.6.dist-info/top_level.txt
