Metadata-Version: 2.0
Name: jupyweave
Version: 0.2.6
Summary: Dynamic report generator
Home-page: https://github.com/jablonskim/jupyweave
Author: Mateusz Jablonski
Author-email: mjablonski92@gmail.com
License: MIT
Keywords: jupyweave literate programming
Platform: UNKNOWN
Classifier: Development Status :: 3 - Alpha
Classifier: Intended Audience :: Developers
Classifier: Topic :: Software Development :: Build Tools
Classifier: Topic :: Documentation
Classifier: Topic :: Text Processing :: Markup
Classifier: License :: OSI Approved :: MIT License
Classifier: Programming Language :: Python :: 3
Classifier: Programming Language :: Python :: 3.3
Classifier: Programming Language :: Python :: 3.4
Classifier: Programming Language :: Python :: 3.5
Requires-Dist: jupyter
Requires-Dist: jupyter-client
Requires-Dist: pygments
